pieraknet/__init__.py
pieraknet/__main__.py
pieraknet/buffer.py
pieraknet/connection.py
pieraknet/protocol_info.py
pieraknet/server.py
pieraknet/handlers/__init__.py
pieraknet/handlers/acknowledgement.py
pieraknet/handlers/connection_request.py
pieraknet/handlers/disconnect.py
pieraknet/handlers/established_connection.py
pieraknet/handlers/fragmented_frame.py
pieraknet/handlers/frame.py
pieraknet/handlers/frame_set.py
pieraknet/handlers/game_packet.py
pieraknet/handlers/new_incoming_connection.py
pieraknet/handlers/offline_ping.py
pieraknet/handlers/online_ping.py
pieraknet/handlers/open_connection_request_1.py
pieraknet/handlers/open_connection_request_2.py
pieraknet/handlers/packet_loss.py
pieraknet/handlers/unknown_packet.py
pieraknet/packets/__init__.py
pieraknet/packets/acknowledgement.py
pieraknet/packets/connection_request.py
pieraknet/packets/connection_request_accepted.py
pieraknet/packets/disconnect.py
pieraknet/packets/frame_set.py
pieraknet/packets/incompatible_protocol.py
pieraknet/packets/new_incoming_connection.py
pieraknet/packets/offline_ping.py
pieraknet/packets/offline_pong.py
pieraknet/packets/online_ping.py
pieraknet/packets/online_pong.py
pieraknet/packets/open_connection_reply_1.py
pieraknet/packets/open_connection_reply_2.py
pieraknet/packets/open_connection_request_1.py
pieraknet/packets/open_connection_request_2.py
pieraknet/packets/packet.py
PieRakNet-2.3.2.1.dist-info/LICENSE
PieRakNet-2.3.2.1.dist-info/METADATA
PieRakNet-2.3.2.1.dist-info/WHEEL
PieRakNet-2.3.2.1.dist-info/top_level.txt
PieRakNet-2.3.2.1.dist-info/RECORD
