Metadata-Version: 2.1
Name: PieRakNet
Version: 2.3.2.1
Author: LapisMYT, andiricum2, soyelmismo, UCYT5040, Inaay
License: GNU GENERAL PUBLIC LICENSE
Project-URL: Homepage, https://github.com/PieMC-Dev/PieRakNet
Keywords: python,python3,raknet,rak-net,mcpe,bedrock,rak_net,piemc,pieraknet,network,protocol,games
Classifier: Development Status :: 3 - Alpha
Classifier: License :: OSI Approved :: GNU General Public License v3 (GPLv3)
Classifier: Programming Language :: Python :: 3.11
Classifier: Topic :: Internet
Classifier: Topic :: Games/Entertainment
Classifier: Topic :: Software Development :: Libraries :: Python Modules
Classifier: Topic :: System :: Networking
License-File: LICENSE
